axoryai/__init__.py
axoryai/client.py
axoryai/exceptions.py
axory-0.1.4.dist-info/METADATA
axory-0.1.4.dist-info/WHEEL
axory-0.1.4.dist-info/top_level.txt
axory-0.1.4.dist-info/RECORD
